BrainStrokeClassifier.py
BrainStrokeClassifier-0.2.2.dist-info/LICENSE.txt
BrainStrokeClassifier-0.2.2.dist-info/METADATA
BrainStrokeClassifier-0.2.2.dist-info/WHEEL
BrainStrokeClassifier-0.2.2.dist-info/top_level.txt
BrainStrokeClassifier-0.2.2.dist-info/RECORD
