Metadata-Version: 2.1
Name: BrainStrokeClassifier
Version: 0.2.2
Summary: Brain Stroke Classfier using Machine Learning!
Home-page: https://github.com/MUmairAB/BrainStrokeClassifier.git
Author: Umair Akram
License: UNKNOWN
Keywords: stroke,brain stroke,brain stroke prediction,stroke prediction,umair akram,the umair akram,trained model,xgboost
Platform: UNKNOWN
Classifier: Programming Language :: Python :: 3
Classifier: License :: OSI Approved :: MIT License
Classifier: Operating System :: OS Independent
Requires-Python: >=3.9
License-File: LICENSE.txt
Requires-Dist: numpy (>=1.21.5)
Requires-Dist: pandas (>=1.5.3)
Requires-Dist: scikit-learn (>=1.2.1)
Requires-Dist: xgboost (==1.7.4)
Requires-Dist: pickle-mixin (==1.0.2)
